{"0": {"Profile": "https://dbkpop.com/group/girls-generation/", "Name": "Girls' Generation", "Short Name": "SNSD", "Korean Name": "\uc18c\ub140\uc2dc\ub300", "Debut": "2007-08-05", "Company": "SM", "Current Member Count": "5", "Original Member Count": "9", "FanClub": "SONE", "Active": "Yes", "Views": "148.849.974", "Likes": "1.443.177"}, "1": {"Profile": "", "Name": "KARA", "Short Name": "", "Korean Name": "\uce74\ub77c", "Debut": "2007-03-29", "Company": "DSP", "Current Member Count": "4", "Original Member Count": "5", "FanClub": "Kamilia", "Active": "No"}, "2": {"Profile": "", "Name": "2NE1", "Short Name": "", "Korean Name": "\ud22c\uc560\ub2c8\uc6d0", "Debut": "2009-05-06", "Company": "YG", "Current Member Count": "4", "Original Member Count": "4", "FanClub": "Blackjack", "Active": "No", "Views": "1.508.008.386", "Likes": "13.890.056"}, "3": {"Profile": "https://dbkpop.com/group/t-ara/", "Name": "T-ara", "Short Name": "", "Korean Name": "\ud2f0\uc544\ub77c", "Debut": "2009-07-29", "Company": "MBK", "Current Member Count": "4", "Original Member Count": "6", "FanClub": "QUEEN'S", "Active": "Hiatus", "Views": "785.476.394", "Likes": "5.681.482"}, "4": {"Profile": "https://dbkpop.com/group/sistar/", "Name": "SISTAR", "Short Name": "", "Korean Name": "\uc528\uc2a4\ud0c0", "Debut": "2010-03-06", "Company": "Starship", "Current Member Count": "4", "Original Member Count": "4", "FanClub": "STAR1", "Active": "No", "Views": "840.702.716", "Likes": "5.401.660"}, "5": {"Profile": "", "Name": "4Minute", "Short Name": "", "Korean Name": "\ud3ec\ubbf8\ub2db", "Debut": "2009-06-15", "Company": "Cube", "Current Member Count": "5", "Original Member Count": "5", "FanClub": "4nia", "Active": "No", "Views": "725.338.386", "Likes": "6.364.660"}, "6": {"Profile": "https://dbkpop.com/group/apink/", "Name": "Apink", "Short Name": "", "Korean Name": "\uc5d0\uc774\ud551\ud06c", "Debut": "2011-04-19", "Company": "Plan A", "Current Member Count": "6", "Original Member Count": "7", "FanClub": "Pink Panda", "Active": "Yes", "Views": "845.695.326", "Likes": "9.173.569"}, "7": {"Profile": "", "Name": "Brown Eyed Girls", "Short Name": "B.E.G.", "Korean Name": "\ube0c\ub77c\uc6b4 \uc544\uc774\ub4dc \uac78\uc2a4", "Debut": "2006-03-02", "Company": "Mystic", "Current Member Count": "4", "Original Member Count": "4", "FanClub": "Everlasting", "Active": "Yes", "Views": "154.980.627", "Likes": "1.359.435"}, "8": {"Profile": "https://dbkpop.com/group/after-school/", "Name": "After School", "Short Name": "", "Korean Name": "\uc560\ud504\ud130\uc2a4\ucfe8", "Debut": "2009-01-15", "Company": "Pledis", "Current Member Count": "6", "Original Member Count": "5", "FanClub": "Playgirlz", "Active": "No"}, "9": {"Profile": "https://dbkpop.com/group/aoa/", "Name": "AOA", "Short Name": "", "Korean Name": "\uc5d0\uc774\uc624\uc5d0\uc774", "Debut": "2012-07-30", "Company": "FNC", "Current Member Count": "4", "Original Member Count": "8", "FanClub": "ELVIS", "Active": "Yes", "Views": "776.252.553", "Likes": "6.115.382"}, "10": {"Profile": "https://dbkpop.com/group/dal-shabet/", "Name": "Dal Shabet", "Short Name": "", "Korean Name": "\ub2ec\uc0e4\ubcb3", "Debut": "2011-01-03", "Company": "Happy Face", "Current Member Count": "4", "Original Member Count": "6", "FanClub": "Darling", "Active": "Hiatus"}, "11": {"Profile": "https://dbkpop.com/group/exid/", "Name": "EXID", "Short Name": "", "Korean Name": "\uc774\uc5d1\uc2a4\uc544\uc774\ub514", "Debut": "2012-02-16", "Company": "Yedang", "Current Member Count": "5", "Original Member Count": "6", "FanClub": "LEGO", "Active": "Yes", "Views": "734.995.537", "Likes": "9.523.290"}, "12": {"Profile": "https://dbkpop.com/group/girls-day/", "Name": "Girl's Day", "Short Name": "GsD", "Korean Name": "\uac78\uc2a4\ub370\uc774", "Debut": "2010-07-09", "Company": "DreamT", "Current Member Count": "4", "Original Member Count": "5", "FanClub": "Dai5y", "Active": "Hiatus", "Views": "487.716.652", "Likes": "3.524.794"}, "13": {"Profile": "https://dbkpop.com/group/wonder-girls/", "Name": "Wonder Girls", "Short Name": "WG", "Korean Name": "\uc6d0\ub354\uac78\uc2a4", "Debut": "2007-02-13", "Company": "JYP", "Current Member Count": "4", "Original Member Count": "5", "FanClub": "Wonderful", "Active": "No", "Views": "449.255.696", "Likes": "4.044.740"}, "14": {"Profile": "", "Name": "miss A", "Short Name": "", "Korean Name": "\ubbf8\uc4f0\uc5d0\uc774", "Debut": "2010-07-01", "Company": "JYP", "Current Member Count": "3", "Original Member Count": "4", "FanClub": "Say A", "Active": "No", "Views": "446.648.028", "Likes": "3.407.299"}, "15": {"Profile": "https://dbkpop.com/group/9muses-nine-muses/", "Name": "9Muses", "Short Name": "Nine Muses", "Korean Name": "\ub098\uc778\ubba4\uc9c0\uc2a4", "Debut": "2010-08-12", "Company": "Star Empire", "Current Member Count": "4", "Original Member Count": "9", "FanClub": "MINE", "Active": "No", "Views": "101.540.718", "Likes": "941.763"}, "16": {"Profile": "", "Name": "Crayon Pop", "Short Name": "", "Korean Name": "\ud06c\ub808\uc6a9\ud31d", "Debut": "2012-07-17", "Company": "Chrome", "Current Member Count": "4", "Original Member Count": "5", "FanClub": "", "Active": "No", "Views": "167.671.091", "Likes": "1.176.371"}, "17": {"Profile": "", "Name": "D-Unit", "Short Name": "", "Korean Name": "\ub514\uc720\ub2db", "Debut": "2012-08-01", "Company": "D-Business", "Current Member Count": "2", "Original Member Count": "3", "FanClub": "Unique", "Active": "No"}, "18": {"Profile": "", "Name": "D.Holic", "Short Name": "", "Korean Name": "\ub514\ud640\ub9ad", "Debut": "2014-10-29", "Company": "H.Mate", "Current Member Count": "4", "Original Member Count": "5", "FanClub": "", "Active": "No"}, "19": {"Profile": "", "Name": "Davichi", "Short Name": "", "Korean Name": "\ub2e4\ube44\uce58", "Debut": "2008-02-04", "Company": "CJ E&M", "Current Member Count": "2", "Original Member Count": "2", "FanClub": "", "Active": "Yes", "Views": "394.445.368", "Likes": "2.580.313"}, "20": {"Profile": "", "Name": "BESTie", "Short Name": "", "Korean Name": "\ubca0\uc2a4\ud2f0", "Debut": "2013-07-11", "Company": "YNB", "Current Member Count": "4", "Original Member Count": "4", "FanClub": "BESTiny", "Active": "No"}, "21": {"Profile": "https://dbkpop.com/group/april/", "Name": "April", "Short Name": "", "Korean Name": "\uc5d0\uc774\ud504\ub9b4", "Debut": "2015-08-24", "Company": "DSP", "Current Member Count": "6", "Original Member Count": "6", "FanClub": "Fineapple", "Active": "No", "Views": "80.762.538", "Likes": "1.351.411"}, "22": {"Profile": "https://dbkpop.com/group/clc/", "Name": "CLC", "Short Name": "", "Korean Name": "\uc528\uc5d8\uc528", "Debut": "2015-03-19", "Company": "Cube", "Current Member Count": "5", "Original Member Count": "5", "FanClub": "Chesire", "Active": "Yes", "Views": "386.420.202", "Likes": "9.372.618"}, "23": {"Profile": "https://dbkpop.com/group/wjsn-cosmic-girls/", "Name": "WJSN", "Short Name": "Cosmic Girls", "Korean Name": "\uc6b0\uc8fc\uc18c\ub140", "Debut": "2016-02-25", "Company": "Starship", "Current Member Count": "13", "Original Member Count": "12", "FanClub": "Ujung", "Active": "Yes", "Views": "191.787.142", "Likes": "3.255.249"}, "24": {"Profile": "https://dbkpop.com/group/brave-girls/", "Name": "Brave Girls", "Short Name": "", "Korean Name": "\ube0c\ub808\uc774\ube0c\uac78\uc2a4", "Debut": "2011-04-08", "Company": "Brave", "Current Member Count": "4", "Original Member Count": "5", "FanClub": "", "Active": "Yes", "Views": "182.589.537", "Likes": "3.596.976"}, "25": {"Profile": "", "Name": "Blady", "Short Name": "", "Korean Name": "\ube14\ub808\uc774\ub514", "Debut": "2011-05-16", "Company": "Star Planet", "Current Member Count": "5", "Original Member Count": "4", "FanClub": "Hi ade", "Active": "No"}, "26": {"Profile": "", "Name": "Bob Girls", "Short Name": "", "Korean Name": "\ub2e8\ubc1c\uba38\ub9ac", "Debut": "2014-06-10", "Company": "Chrome", "Current Member Count": "4", "Original Member Count": "4", "FanClub": "", "Active": "No"}, "27": {"Profile": "", "Name": "C-REAL", "Short Name": "", "Korean Name": "\uc528\ub9ac\uc5bc", "Debut": "2011-10-11", "Company": "NAP", "Current Member Count": "3", "Original Member Count": "5", "FanClub": "", "Active": "No"}, "28": {"Profile": "", "Name": "ChoColat", "Short Name": "", "Korean Name": "\uc1fc\ucf5c\ub77c", "Debut": "2011-08-16", "Company": "Paramount", "Current Member Count": "5", "Original Member Count": "5", "FanClub": "Chocolatier", "Active": "No"}, "29": {"Profile": "", "Name": "Badkiz", "Short Name": "", "Korean Name": "\ubc30\ub4dc\ud0a4\uc988", "Debut": "2014-03-24", "Company": "Zoo", "Current Member Count": "5", "Original Member Count": "5", "FanClub": "", "Active": "No"}, "30": {"Profile": "", "Name": "4TEN", "Short Name": "", "Korean Name": "\ud3ec\ud150", "Debut": "2014-08-26", "Company": "Jungle", "Current Member Count": "4", "Original Member Count": "4", "FanClub": "", "Active": "No"}, "31": {"Profile": "", "Name": "15&", "Short Name": "", "Korean Name": "\ud53c\ud504\ud2f4\uc564\ub4dc", "Debut": "2012-10-05", "Company": "JYP", "Current Member Count": "2", "Original Member Count": "2", "FanClub": "", "Active": "No"}, "32": {"Profile": "https://dbkpop.com/group/dia/", "Name": "DIA", "Short Name": "", "Korean Name": "\ub2e4\uc774\uc544", "Debut": "2015-07-14", "Company": "MBK", "Current Member Count": "7", "Original Member Count": "7", "FanClub": "AID", "Active": "Yes", "Views": "50.075.653", "Likes": "993.615"}, "33": {"Profile": "", "Name": "EvoL", "Short Name": "", "Korean Name": "\uc774\ube14", "Debut": "2012-08-10", "Company": "Stardom", "Current Member Count": "5", "Original Member Count": "5", "FanClub": "Voller", "Active": "No"}, "34": {"Profile": "https://dbkpop.com/group/oh-my-girl/", "Name": "Oh My Girl", "Short Name": "OHMG", "Korean Name": "\uc624\ub9c8\uc774\uac78", "Debut": "2015-04-21", "Company": "WM", "Current Member Count": "7", "Original Member Count": "8", "FanClub": "Miracle", "Active": "Yes", "Views": "435.555.505", "Likes": "5.019.674"}, "35": {"Profile": "", "Name": "f(x)", "Short Name": "", "Korean Name": "\uc5d0\ud504\uc5d1\uc2a4", "Debut": "2009-08-24", "Company": "SM", "Current Member Count": "4", "Original Member Count": "5", "FanClub": "MeU", "Active": "No"}, "36": {"Profile": "https://dbkpop.com/group/red-velvet/", "Name": "Red Velvet", "Short Name": "RV", "Korean Name": "\ub808\ub4dc\ubca8\ubcb3", "Debut": "2014-08-01", "Company": "SM", "Current Member Count": "5", "Original Member Count": "4", "FanClub": "", "Active": "Yes", "Views": "156.412.734", "Likes": "5.653.771"}, "37": {"Profile": "", "Name": "Rainbow", "Short Name": "", "Korean Name": "\ub808\uc778\ubcf4\uc6b0", "Debut": "-0001-11-30", "Company": "DSP", "Current Member Count": "7", "Original Member Count": "7", "FanClub": "", "Active": "No"}, "38": {"Profile": "https://dbkpop.com/group/twice/", "Name": "TWICE", "Short Name": "", "Korean Name": "\ud2b8\uc640\uc774\uc2a4", "Debut": "2015-10-20", "Company": "JYP", "Current Member Count": "9", "Original Member Count": "9", "FanClub": "Once", "Active": "Yes", "Views": "9.081.517.045", "Likes": "121.105.020"}, "39": {"Profile": "", "Name": "Tahiti", "Short Name": "", "Korean Name": "\ud0c0\ud788\ud2f0", "Debut": "2012-06-23", "Company": "J-line", "Current Member Count": "5", "Original Member Count": "6", "FanClub": "", "Active": "No"}, "40": {"Profile": "", "Name": "Fiestar", "Short Name": "", "Korean Name": "\ud53c\uc5d0\uc2a4\ud0c0", "Debut": "2012-08-31", "Company": "LOEN", "Current Member Count": "5", "Original Member Count": "6", "FanClub": "Let's", "Active": "No"}, "41": {"Profile": "https://dbkpop.com/group/hello-venus/", "Name": "Hello Venus", "Short Name": "HV", "Korean Name": "\ud5ec\ub85c\ube44\ub108\uc2a4", "Debut": "2012-05-09", "Company": "Fantagio", "Current Member Count": "6", "Original Member Count": "6", "FanClub": "Hello Cupid", "Active": "No"}, "42": {"Profile": "", "Name": "Ladies' Code", "Short Name": "LC", "Korean Name": "\ub808\uc774\ub514\uc2a4 \ucf54\ub4dc", "Debut": "2013-03-07", "Company": "Polaris", "Current Member Count": "3", "Original Member Count": "5", "FanClub": "Lavely", "Active": "Hiatus", "Views": "50.955.943", "Likes": "1.007.154"}, "43": {"Profile": "https://dbkpop.com/group/laboum/", "Name": "Laboum", "Short Name": "", "Korean Name": "\ub77c\ubd90", "Debut": "2014-08-27", "Company": "NH", "Current Member Count": "4", "Original Member Count": "6", "FanClub": "Latte", "Active": "Yes"}, "44": {"Profile": "https://dbkpop.com/group/lovelyz/", "Name": "Lovelyz", "Short Name": "", "Korean Name": "\ub7ec\ube14\ub9ac\uc988", "Debut": "2014-11-17", "Company": "Woollim", "Current Member Count": "8", "Original Member Count": "8", "FanClub": "Lovelinus", "Active": "No", "Views": "162.239.141", "Likes": "2.029.745"}, "45": {"Profile": "", "Name": "Wassup", "Short Name": "", "Korean Name": "\uc640\uc379", "Debut": "2013-08-07", "Company": "Mafia", "Current Member Count": "7", "Original Member Count": "7", "FanClub": "", "Active": "No"}, "46": {"Profile": "https://dbkpop.com/group/gugudan/", "Name": "Gugudan", "Short Name": "", "Korean Name": "\uad6c\uad6c\ub2e8", "Debut": "2016-06-28", "Company": "Jellyfish", "Current Member Count": "8", "Original Member Count": "9", "FanClub": "", "Active": "No", "Views": "52.479.838", "Likes": "1.142.757"}, "47": {"Profile": "https://dbkpop.com/group/gfriend/", "Name": "Gfriend", "Short Name": "", "Korean Name": "\uc5ec\uc790\uce5c\uad6c", "Debut": "2015-01-15", "Company": "Source", "Current Member Count": "6", "Original Member Count": "6", "FanClub": "Buddy", "Active": "No", "Views": "919.269.488", "Likes": "16.886.968"}, "48": {"Profile": "", "Name": "Unicorn", "Short Name": "", "Korean Name": "\uc720\ub2c8\ucf58", "Debut": "2015-09-03", "Company": "Cartoon Blue", "Current Member Count": "4", "Original Member Count": "5", "FanClub": "", "Active": "No"}, "49": {"Profile": "https://dbkpop.com/group/berry-good/", "Name": "Berry Good", "Short Name": "", "Korean Name": "\ubca0\ub9ac\uad7f", "Debut": "2014-05-21", "Company": "Asia Bridge", "Current Member Count": "6", "Original Member Count": "5", "FanClub": "", "Active": "No"}, "50": {"Profile": "", "Name": "BLACKPINK", "Short Name": "", "Korean Name": "\ube14\ub799\ud551\ud06c", "Debut": "2016-08-08", "Company": "YG", "Current Member Count": "4", "Original Member Count": "4", "FanClub": "", "Active": "Yes", "Views": "13.631.851.608", "Likes": "202.213.071"}, "51": {"Profile": "", "Name": "F-ve Dolls", "Short Name": "5Dolls", "Korean Name": "\ud30c\uc774\ube0c\ub3cc\uc2a4", "Debut": "2011-01-20", "Company": "MBK", "Current Member Count": "6", "Original Member Count": "5", "FanClub": "", "Active": "No"}, "52": {"Profile": "", "Name": "GI", "Short Name": "Global Icon", "Korean Name": "\uc9c0\uc544\uc774", "Debut": "2013-04-03", "Company": "Simtong", "Current Member Count": "3", "Original Member Count": "5", "FanClub": "", "Active": "No", "Views": "26.542.306", "Likes": "1.113.442"}, "53": {"Profile": "", "Name": "GLAM", "Short Name": "", "Korean Name": "\uae00\ub7a8", "Debut": "2012-07-16", "Company": "Big Hit", "Current Member Count": "4", "Original Member Count": "4", "FanClub": "", "Active": "No"}, "54": {"Profile": "", "Name": "GP Basic", "Short Name": "", "Korean Name": "\uc9c0\ud53c \ubca0\uc774\uc9c1", "Debut": "2011-03-18", "Company": "Jacyhan", "Current Member Count": "4", "Original Member Count": "6", "FanClub": "Spade", "Active": "No"}, "55": {"Profile": "", "Name": "Jewelry", "Short Name": "", "Korean Name": "\uc96c\uc5bc\ub9ac", "Debut": "2001-03-30", "Company": "Star Empire", "Current Member Count": "4", "Original Member Count": "4", "FanClub": "", "Active": "No"}, "56": {"Profile": "", "Name": "Baby V.O.X", "Short Name": "", "Korean Name": "\ubca0\uc774\ube44\ubcf5\uc2a4", "Debut": "1997-07-05", "Company": "DR Music", "Current Member Count": "5", "Original Member Count": "5", "FanClub": "", "Active": "No"}, "57": {"Profile": "https://dbkpop.com/group/mamamoo/", "Name": "Mamamoo", "Short Name": "", "Korean Name": "\ub9c8\ub9c8\ubb34", "Debut": "2014-06-18", "Company": "RBW", "Current Member Count": "4", "Original Member Count": "4", "FanClub": "Moomoo", "Active": "Yes", "Views": "1.992.660.775", "Likes": "43.182.754"}, "58": {"Profile": "https://dbkpop.com/group/melodyday/", "Name": "Melody Day", "Short Name": "", "Korean Name": "\uba5c\ub85c\ub514\ub370\uc774", "Debut": "2014-02-25", "Company": "Cre.Ker", "Current Member Count": "4", "Original Member Count": "3", "FanClub": "", "Active": "No"}, "59": {"Profile": "", "Name": "Minx", "Short Name": "", "Korean Name": "\ubc0d\uc2a4", "Debut": "2014-09-18", "Company": "Happy Face", "Current Member Count": "5", "Original Member Count": "5", "FanClub": "", "Active": "No"}, "60": {"Profile": "", "Name": "Pungdeng-E", "Short Name": "", "Korean Name": "\ud48d\ub385\uc774", "Debut": "2013-12-11", "Company": "DOMA", "Current Member Count": "3", "Original Member Count": "3", "FanClub": "", "Active": "Hiatus"}, "61": {"Profile": "", "Name": "Tiny-G", "Short Name": "", "Korean Name": "\ud0c0\uc774\ub2c8\uc9c0", "Debut": "2012-08-23", "Company": "GNG", "Current Member Count": "3", "Original Member Count": "4", "FanClub": "", "Active": "No"}, "62": {"Profile": "", "Name": "Two X", "Short Name": "", "Korean Name": "\ud22c\uc5d1\uc2a4", "Debut": "2012-08-20", "Company": "J. Tune", "Current Member Count": "4", "Original Member Count": "5", "FanClub": "", "Active": "No"}, "63": {"Profile": "https://dbkpop.com/group/stellar/", "Name": "Stellar", "Short Name": "", "Korean Name": "\uc2a4\ud154\ub77c", "Debut": "2011-08-28", "Company": "Pascal", "Current Member Count": "4", "Original Member Count": "4", "FanClub": "Twinkle", "Active": "No"}, "64": {"Profile": "https://dbkpop.com/group/secret/", "Name": "SECRET", "Short Name": "", "Korean Name": "\uc2dc\ud06c\ub9bf", "Debut": "2009-10-13", "Company": "TS", "Current Member Count": "3", "Original Member Count": "4", "FanClub": "Secret Time", "Active": "No", "Views": "97.437.026", "Likes": "5.171.212"}, "65": {"Profile": "https://dbkpop.com/group/sonamoo/", "Name": "Sonamoo", "Short Name": "", "Korean Name": "\uc18c\ub098\ubb34", "Debut": "2014-12-29", "Company": "TS", "Current Member Count": "5", "Original Member Count": "7", "FanClub": "Solbangul", "Active": "No"}, "66": {"Profile": "", "Name": "Rania", "Short Name": "", "Korean Name": "\ub77c\ub2c8\uc544", "Debut": "2011-04-06", "Company": "DR", "Current Member Count": "5", "Original Member Count": "8", "FanClub": "", "Active": "No"}, "67": {"Profile": "", "Name": "Rubber Soul", "Short Name": "", "Korean Name": "\ub7ec\ubc84\uc18c\uc6b8", "Debut": "2015-02-10", "Company": "Happy Tribe", "Current Member Count": "2", "Original Member Count": "3", "FanClub": "", "Active": "Yes"}, "68": {"Profile": "", "Name": "Playback", "Short Name": "", "Korean Name": "\ud50c\ub808\uc774\ubc31", "Debut": "2015-06-25", "Company": "Coridel", "Current Member Count": "5", "Original Member Count": "4", "FanClub": "", "Active": "Yes"}, "69": {"Profile": "", "Name": "SPICA", "Short Name": "", "Korean Name": "\uc2a4\ud53c\uce74", "Debut": "2012-02-07", "Company": "CJ E&M", "Current Member Count": "5", "Original Member Count": "5", "FanClub": "Mercury", "Active": "No"}, "70": {"Profile": "", "Name": "Sunny Hill", "Short Name": "", "Korean Name": "\uc368\ub2c8\ud790", "Debut": "2007-09-20", "Company": "Nega", "Current Member Count": "4", "Original Member Count": "5", "FanClub": "", "Active": "No"}, "71": {"Profile": "https://dbkpop.com/group/momoland/", "Name": "Momoland", "Short Name": "", "Korean Name": "\ubaa8\ubaa8\ub79c\ub4dc", "Debut": "2016-11-09", "Company": "Double Kick", "Current Member Count": "6", "Original Member Count": "7", "FanClub": "", "Active": "Yes", "Views": "1.955.036.216", "Likes": "17.463.636"}, "72": {"Profile": "https://dbkpop.com/group/bonus-baby/", "Name": "Bonus Baby", "Short Name": "", "Korean Name": "\ubcf4\ub108\uc2a4\ubca0\uc774\ube44", "Debut": "2017-01-01", "Company": "Maroo", "Current Member Count": "6", "Original Member Count": "6", "FanClub": "", "Active": "No"}, "73": {"Profile": "", "Name": "myB", "Short Name": "", "Korean Name": "\ub9c8\uc774\ube44", "Debut": "2015-08-25", "Company": "Maroo", "Current Member Count": "6", "Original Member Count": "6", "FanClub": "", "Active": "No"}, "74": {"Profile": "", "Name": "S.E.S", "Short Name": "", "Korean Name": "\uc5d0\uc2a4.\uc774.\uc5d0\uc2a4", "Debut": "1997-11-01", "Company": "SM", "Current Member Count": "3", "Original Member Count": "3", "FanClub": "", "Active": "No"}, "75": {"Profile": "", "Name": "The Grace", "Short Name": "CSJH", "Korean Name": "\ucc9c\uc0c1\uc9c0\ud76c", "Debut": "2005-04-29", "Company": "SM", "Current Member Count": "3", "Original Member Count": "4", "FanClub": "", "Active": "No"}, "76": {"Profile": "", "Name": "Mixx", "Short Name": "", "Korean Name": "\ubbf9\uc2a4", "Debut": "2016-05-02", "Company": "Chiko", "Current Member Count": "5", "Original Member Count": "4", "FanClub": "", "Active": "No", "Views": "52.216.926", "Likes": "1.475.894"}, "77": {"Profile": "https://dbkpop.com/group/loona/", "Name": "Loona", "Short Name": "LOO\u03a0\u0394", "Korean Name": "\uc774\ub2ec\uc758 \uc18c\ub140", "Debut": "2018-08-20", "Company": "Blockberry", "Current Member Count": "12", "Original Member Count": "12", "FanClub": "", "Active": "Yes", "Views": "477.848.641", "Likes": "12.916.587"}, "78": {"Profile": "https://dbkpop.com/group/pristin/", "Name": "Pristin", "Short Name": "", "Korean Name": "\ud504\ub9ac\uc2a4\ud2f4", "Debut": "2017-03-21", "Company": "Pledis", "Current Member Count": "10", "Original Member Count": "10", "FanClub": "", "Active": "No", "Views": "72.225.508", "Likes": "1.291.975"}, "79": {"Profile": "https://dbkpop.com/group/dream-catcher/", "Name": "DreamCatcher", "Short Name": "", "Korean Name": "\ub4dc\ub9bc\uce90\uccd0", "Debut": "2017-01-13", "Company": "Happy Face", "Current Member Count": "7", "Original Member Count": "7", "FanClub": "", "Active": "Yes", "Views": "419.898.770", "Likes": "12.842.315"}, "80": {"Profile": "", "Name": "S.I.S", "Short Name": "", "Korean Name": "\uc5d0\uc2a4\uc544\uc774\uc5d0\uc2a4", "Debut": "2017-08-25", "Company": "Double X", "Current Member Count": "6", "Original Member Count": "6", "FanClub": "", "Active": "Yes"}, "81": {"Profile": "https://dbkpop.com/group/weki-meki/", "Name": "Weki Meki", "Short Name": "WeMe", "Korean Name": "\uc704\ud0a4\ubbf8\ud0a4", "Debut": "2017-08-08", "Company": "Fantagio", "Current Member Count": "8", "Original Member Count": "8", "FanClub": "", "Active": "Yes", "Views": "120.707.420", "Likes": "3.571.367"}, "82": {"Profile": "", "Name": "ELRIS", "Short Name": "", "Korean Name": "\uc5d8\ub9ac\uc2a4", "Debut": "2017-07-01", "Company": "Hunus", "Current Member Count": "7", "Original Member Count": "5", "FanClub": "", "Active": "Yes"}, "83": {"Profile": "", "Name": "Favorite", "Short Name": "", "Korean Name": "\ud398\uc774\ubc84\ub9bf", "Debut": "2017-07-05", "Company": "Astory", "Current Member Count": "6", "Original Member Count": "6", "FanClub": "", "Active": "Yes"}, "84": {"Profile": "", "Name": "Good Day", "Short Name": "", "Korean Name": "\uad7f\ub370\uc774", "Debut": "2017-08-30", "Company": "C9", "Current Member Count": "10", "Original Member Count": "10", "FanClub": "", "Active": "No"}, "85": {"Profile": "", "Name": "P.O.P", "Short Name": "", "Korean Name": "\ud53c\uc624\ud53c", "Debut": "2017-07-26", "Company": "DWM", "Current Member Count": "6", "Original Member Count": "6", "FanClub": "", "Active": "No"}, "86": {"Profile": "", "Name": "G-reyish", "Short Name": "Greyish", "Korean Name": "\uadf8\ub808\uc774\uc2dc", "Debut": "2017-06-01", "Company": "Elijah", "Current Member Count": "4", "Original Member Count": "4", "FanClub": "", "Active": "Yes"}, "87": {"Profile": "", "Name": "CoCoSoRi", "Short Name": "", "Korean Name": "\ucf54\ucf54\uc18c\ub9ac", "Debut": "2016-01-05", "Company": "MOLE", "Current Member Count": "2", "Original Member Count": "2", "FanClub": "", "Active": "No"}, "88": {"Profile": "https://dbkpop.com/group/bolbbalgan4/", "Name": "Bolbbalgan4", "Short Name": "BOL4", "Korean Name": "\ubcfc\ube68\uac04\uc0ac\ucd98\uae30", "Debut": "2016-04-22", "Company": "Shofar", "Current Member Count": "1", "Original Member Count": "2", "FanClub": "", "Active": "Yes", "Views": "566.009.310", "Likes": "7.470.817"}, "89": {"Profile": "", "Name": "Bloomy", "Short Name": "", "Korean Name": "\ube14\ub8e8\ubbf8", "Debut": "2016-02-01", "Company": "DS", "Current Member Count": "4", "Original Member Count": "4", "FanClub": "", "Active": "Yes"}, "90": {"Profile": "", "Name": "Bulldok", "Short Name": "", "Korean Name": "\ubd88\ub3c5", "Debut": "2016-10-20", "Company": "Kconic", "Current Member Count": "5", "Original Member Count": "3", "FanClub": "", "Active": "No"}, "91": {"Profile": "", "Name": "Highteen", "Short Name": "", "Korean Name": "\ud558\uc774\ud2f4", "Debut": "2016-10-14", "Company": "Elijah", "Current Member Count": "4", "Original Member Count": "4", "FanClub": "", "Active": "Yes"}, "92": {"Profile": "", "Name": "Matilda", "Short Name": "", "Korean Name": "\ub9c8\ud2f8\ub2e4", "Debut": "2016-03-18", "Company": "Box", "Current Member Count": "4", "Original Member Count": "4", "FanClub": "", "Active": "No"}, "93": {"Profile": "", "Name": "Dorothy", "Short Name": "", "Korean Name": "\ub3c4\ub85c\uc2dc", "Debut": "2016-08-16", "Company": "Leek Mill", "Current Member Count": "3", "Original Member Count": "5", "FanClub": "", "Active": "No"}, "94": {"Profile": "", "Name": "OhBliss", "Short Name": "", "Korean Name": "\uc624\ube14\ub9ac\uc2a4", "Debut": "2016-10-17", "Company": "JT Corea", "Current Member Count": "5", "Original Member Count": "5", "FanClub": "", "Active": "Yes"}, "95": {"Profile": "", "Name": "Girls Girls", "Short Name": "", "Korean Name": "\uc5ec\uc790\uc5ec\uc790", "Debut": "2015-12-09", "Company": "H Brothers", "Current Member Count": "4", "Original Member Count": "5", "FanClub": "", "Active": "No"}, "96": {"Profile": "", "Name": "O21", "Short Name": "", "Korean Name": "\uc624\ud22c\uc6d0", "Debut": "2016-06-21", "Company": "Houxiu", "Current Member Count": "3", "Original Member Count": "6", "FanClub": "", "Active": "No"}, "97": {"Profile": "", "Name": "Apple.B", "Short Name": "", "Korean Name": "\uc560\ud50c\ube44", "Debut": "2017-08-01", "Company": "GH", "Current Member Count": "5", "Original Member Count": "5", "FanClub": "", "Active": "No"}, "98": {"Profile": "", "Name": "H.U.B", "Short Name": "HUB", "Korean Name": "\ud5c8\ube0c", "Debut": "2017-02-09", "Company": "New Planet", "Current Member Count": "5", "Original Member Count": "4", "FanClub": "", "Active": "No"}, "99": {"Profile": "https://dbkpop.com/group/hashtag/", "Name": "Hash Tag", "Short Name": "Hashtag", "Korean Name": "\ud574\uc2dc\ud0dc\uadf8", "Debut": "2017-10-11", "Company": "LUK", "Current Member Count": "7", "Original Member Count": "7", "FanClub": "", "Active": "Yes"}, "100": {"Profile": "", "Name": "LipBubble", "Short Name": "", "Korean Name": "\ub9bd\ubc84\ube14", "Debut": "2017-03-22", "Company": "Zenith", "Current Member Count": "7", "Original Member Count": "7", "FanClub": "", "Active": "No"}, "101": {"Profile": "", "Name": "Marmello", "Short Name": "", "Korean Name": "\ub9c8\ub974\uba5c\ub85c", "Debut": "2017-05-24", "Company": "Rolling", "Current Member Count": "5", "Original Member Count": "5", "FanClub": "", "Active": "No"}, "102": {"Profile": "https://dbkpop.com/group/fromis-9/", "Name": "fromis_9", "Short Name": "", "Korean Name": "\ud504\ub85c\ubbf8\uc2a4\ub098\uc778", "Debut": "2018-01-24", "Company": "Off The Record", "Current Member Count": "9", "Original Member Count": "9", "FanClub": "", "Active": "Yes"}, "103": {"Profile": "https://dbkpop.com/group/honey-popcorn/", "Name": "Honey Popcorn", "Short Name": "", "Korean Name": "\ud5c8\ub2c8\ud31d\ucf58", "Debut": "2018-03-21", "Company": "Kyun Create", "Current Member Count": "3", "Original Member Count": "3", "FanClub": "", "Active": "Yes"}, "104": {"Profile": "https://dbkpop.com/group/girlkind/", "Name": "Girlkind", "Short Name": "", "Korean Name": "\uac78\uce74\uc778\ub4dc", "Debut": "2018-01-16", "Company": "Nextlevel", "Current Member Count": "5", "Original Member Count": "5", "FanClub": "", "Active": "Yes"}, "105": {"Profile": "https://dbkpop.com/group/gi-dle/", "Name": "(G)I-DLE", "Short Name": "", "Korean Name": "(\uc5ec\uc790)\uc544\uc774\ub4e4", "Debut": "2018-05-02", "Company": "Cube", "Current Member Count": "6", "Original Member Count": "6", "FanClub": "", "Active": "Yes"}, "106": {"Profile": "https://dbkpop.com/group/gwsn/", "Name": "GWSN", "Short Name": "", "Korean Name": "\uacf5\uc6d0\uc18c\ub140", "Debut": "2018-09-05", "Company": "Kiwi Pop", "Current Member Count": "7", "Original Member Count": "7", "FanClub": "Groo", "Active": "Yes", "Views": "103.206.101", "Likes": "1.009.098"}, "107": {"Profile": "https://dbkpop.com/group/izone/", "Name": "IZ*ONE", "Short Name": "IZONE", "Korean Name": "\uc544\uc774\uc988\uc6d0", "Debut": "2018-10-29", "Company": "Off The Record", "Current Member Count": "12", "Original Member Count": "12", "FanClub": "", "Active": "No", "Views": "769.255.086", "Likes": "13.091.750"}, "108": {"Profile": "https://dbkpop.com/group/nature/", "Name": "Nature", "Short Name": "", "Korean Name": "\ub124\uc774\ucc98", "Debut": "2018-08-03", "Company": "n.CH", "Current Member Count": "9", "Original Member Count": "9", "FanClub": "", "Active": "Yes", "Views": "52.692.450", "Likes": "1.047.606"}, "109": {"Profile": "https://dbkpop.com/group/uni-t/", "Name": "Uni.T", "Short Name": "", "Korean Name": "\uc720\ub2c8\ud2f0", "Debut": "2018-05-18", "Company": "Unit Culture", "Current Member Count": "8", "Original Member Count": "9", "FanClub": "", "Active": "No"}, "110": {"Profile": "", "Name": "We Girls", "Short Name": "", "Korean Name": "\uc704\uac78\uc2a4", "Debut": "2018-08-31", "Company": "Afternoon", "Current Member Count": "8", "Original Member Count": "8", "FanClub": "", "Active": "Yes"}, "111": {"Profile": "", "Name": "Gawi Bawi Bo", "Short Name": "GBB", "Korean Name": "\uc9c0\ube44\ube44", "Debut": "2018-05-01", "Company": "LOUDers", "Current Member Count": "5", "Original Member Count": "5", "FanClub": "", "Active": "Yes"}, "112": {"Profile": "https://dbkpop.com/group/cherry-bullet/", "Name": "Cherry Bullet", "Short Name": "", "Korean Name": "\uccb4\ub9ac\ube14\ub81b", "Debut": "2019-01-21", "Company": "FNC", "Current Member Count": "7", "Original Member Count": "10", "FanClub": "", "Active": "Yes", "Views": "65.318.054", "Likes": "1.868.002"}, "113": {"Profile": "https://dbkpop.com/group/dreamnote/", "Name": "Dreamnote", "Short Name": "", "Korean Name": "\ub4dc\ub9bc\ub178\ud2b8", "Debut": "2018-11-07", "Company": "iME", "Current Member Count": "6", "Original Member Count": "8", "FanClub": "", "Active": "Yes"}, "114": {"Profile": "", "Name": "Cherry On Top", "Short Name": "", "Korean Name": "\uccb4\ub9ac\uc628\ud0d1", "Debut": "2018-08-09", "Company": "United", "Current Member Count": "4", "Original Member Count": "4", "FanClub": "", "Active": "No"}, "115": {"Profile": "https://dbkpop.com/group/saturday", "Name": "Saturday", "Short Name": "", "Korean Name": "\uc138\ub7ec\ub370\uc774", "Debut": "2018-07-18", "Company": "SD", "Current Member Count": "6", "Original Member Count": "7", "FanClub": "", "Active": "Yes"}, "116": {"Profile": "", "Name": "FLAVOR", "Short Name": "", "Korean Name": "\ud50c\ub808\uc774\ubc84", "Debut": "2018-11-26", "Company": "FENT", "Current Member Count": "3", "Original Member Count": "3", "FanClub": "", "Active": "Yes"}, "117": {"Profile": "https://dbkpop.com/group/pink-fantasy/", "Name": "Pink Fantasy", "Short Name": "", "Korean Name": "\ud551\ud06c\ud310\ud0c0\uc9c0", "Debut": "2018-10-28", "Company": "My Doll", "Current Member Count": "8", "Original Member Count": "8", "FanClub": "", "Active": "Yes"}, "118": {"Profile": "", "Name": "Heygirls", "Short Name": "", "Korean Name": "\ud5e4\uc774\uac78\uc2a4", "Debut": "2017-11-20", "Company": "Moai", "Current Member Count": "4", "Original Member Count": "4", "FanClub": "", "Active": "Yes"}, "119": {"Profile": "", "Name": "ABRY", "Short Name": "", "Korean Name": "\uc5d0\uc774\ube0c\ub9ac", "Debut": "2017-11-15", "Company": "withHC", "Current Member Count": "4", "Original Member Count": "4", "FanClub": "", "Active": "Yes"}, "120": {"Profile": "", "Name": "Rose Finger", "Short Name": "", "Korean Name": "\ub85c\uc988\ud551\uac70", "Debut": "2018-10-03", "Company": "YC:Bros", "Current Member Count": "4", "Original Member Count": "4", "FanClub": "", "Active": "No"}, "121": {"Profile": "", "Name": "Destiny", "Short Name": "", "Korean Name": "\ub370\uc2a4\ud2f0\ub2c8", "Debut": "2018-09-28", "Company": "D-SIDE", "Current Member Count": "4", "Original Member Count": "4", "FanClub": "", "Active": "Yes"}, "122": {"Profile": "https://dbkpop.com/group/purplebeck/", "Name": "PURPLEBECK", "Short Name": "", "Korean Name": "\ud37c\ud50c\ubc31", "Debut": "2019-06-24", "Company": "Majesty", "Current Member Count": "5", "Original Member Count": "5", "FanClub": "Beckies", "Active": "Yes"}, "123": {"Profile": "", "Name": "Kitten Girls", "Short Name": "", "Korean Name": "\ud0a4\ud2bc\uac78\uc2a4", "Debut": "2018-09-04", "Company": "Wannabe", "Current Member Count": "4", "Original Member Count": "4", "FanClub": "", "Active": "No"}, "124": {"Profile": "", "Name": "Camila", "Short Name": "", "Korean Name": "\uce74\ubc00\ub77c", "Debut": "2018-08-29", "Company": "Camila", "Current Member Count": "3", "Original Member Count": "3", "FanClub": "", "Active": "No"}, "125": {"Profile": "", "Name": "Sha Sha", "Short Name": "", "Korean Name": "\uc0e4\uc0e4", "Debut": "2018-02-27", "Company": "Major Ent", "Current Member Count": "6", "Original Member Count": "6", "FanClub": "", "Active": "No"}, "126": {"Profile": "", "Name": "AiRiSu", "Short Name": "", "Korean Name": "\uc544\uc774\ub9ac\uc218", "Debut": "2018-07-25", "Company": "Jang", "Current Member Count": "4", "Original Member Count": "4", "FanClub": "", "Active": "No"}, "127": {"Profile": "", "Name": "Yellow Bee", "Short Name": "", "Korean Name": "\uc610\ub85c\ube44", "Debut": "2017-11-23", "Company": "Addiction", "Current Member Count": "5", "Original Member Count": "5", "FanClub": "", "Active": "No"}, "128": {"Profile": "", "Name": "Wable", "Short Name": "", "Korean Name": "\uc640\ube14", "Debut": "2016-02-17", "Company": "Kiwi", "Current Member Count": "2", "Original Member Count": "2", "FanClub": "", "Active": "Yes"}, "129": {"Profile": "", "Name": "Busters", "Short Name": "", "Korean Name": "\ubc84\uc2a4\ud130\uc988", "Debut": "2017-11-27", "Company": "JTG", "Current Member Count": "5", "Original Member Count": "5", "FanClub": "Bu-Chu", "Active": "Yes"}, "130": {"Profile": "", "Name": "KHAN", "Short Name": "", "Korean Name": "\uce78", "Debut": "2018-05-23", "Company": "Maroo", "Current Member Count": "2", "Original Member Count": "2", "FanClub": "", "Active": "No"}, "131": {"Profile": "", "Name": "GsA", "Short Name": "Girls' Alert", "Korean Name": "\uc18c\ub140\uc8fc\uc758\ubcf4", "Debut": "2017-05-25", "Company": "Roots", "Current Member Count": "5", "Original Member Count": "5", "FanClub": "", "Active": "Yes"}, "132": {"Profile": "", "Name": "Hi Cutie", "Short Name": "", "Korean Name": "\ud558\uc774\ud050\ud2f0", "Debut": "2017-10-12", "Company": "Space", "Current Member Count": "4", "Original Member Count": "5", "FanClub": "", "Active": "Yes"}, "133": {"Profile": "", "Name": "Gavy NJ", "Short Name": "", "Korean Name": "\uac00\ube44\uc5d4\uc81c\uc774", "Debut": "2005-11-11", "Company": "Good Fellas", "Current Member Count": "3", "Original Member Count": "3", "FanClub": "", "Active": "Yes"}, "134": {"Profile": "", "Name": "I.C.E", "Short Name": "", "Korean Name": "\uc544\uc774\uc2a4", "Debut": "2015-11-16", "Company": "HS", "Current Member Count": "3", "Original Member Count": "4", "FanClub": "", "Active": "Yes"}, "135": {"Profile": "", "Name": "Wanna.B", "Short Name": "", "Korean Name": "\uc6cc\ub108\ube44", "Debut": "2014-11-17", "Company": "Zenith", "Current Member Count": "5", "Original Member Count": "4", "FanClub": "Ru.B", "Active": "No"}, "136": {"Profile": "", "Name": "Hint", "Short Name": "", "Korean Name": "\ud78c\ud2b8", "Debut": "2017-03-31", "Company": "Starpro", "Current Member Count": "5", "Original Member Count": "7", "FanClub": "", "Active": "Yes"}, "137": {"Profile": "", "Name": "2EYES", "Short Name": "", "Korean Name": "\ud22c\uc544\uc774\uc988", "Debut": "2013-07-20", "Company": "SidusHQ", "Current Member Count": "4", "Original Member Count": "5", "FanClub": "", "Active": "No"}, "138": {"Profile": "", "Name": "GeeGu", "Short Name": "", "Korean Name": "\uc9c0\uad6c", "Debut": "2017-10-26", "Company": "NOS", "Current Member Count": "7", "Original Member Count": "9", "FanClub": "", "Active": "No"}, "139": {"Profile": "", "Name": "A.DE", "Short Name": "", "Korean Name": "\uc5d0\uc774\ub514\uc774", "Debut": "2016-07-23", "Company": "2ABLE", "Current Member Count": "6", "Original Member Count": "7", "FanClub": "", "Active": "No"}, "140": {"Profile": "https://dbkpop.com/group/itzy/", "Name": "ITZY", "Short Name": "", "Korean Name": "\uc788\uc9c0", "Debut": "2019-02-12", "Company": "JYP", "Current Member Count": "5", "Original Member Count": "5", "FanClub": "Mitzy", "Active": "Yes", "Views": "2.424.290.541", "Likes": "51.783.441"}, "141": {"Profile": "https://dbkpop.com/group/lusty/", "Name": "Lusty", "Short Name": "", "Korean Name": "\ub7ec\uc2a4\ud2f0", "Debut": "2019-06-26", "Company": "babaplay", "Current Member Count": "5", "Original Member Count": "5", "FanClub": "", "Active": "Yes"}, "142": {"Profile": "https://dbkpop.com/group/everglow/", "Name": "Everglow", "Short Name": "", "Korean Name": "\uc5d0\ubc84\uae00\ub85c\uc6b0", "Debut": "2019-03-18", "Company": "Yuehua", "Current Member Count": "6", "Original Member Count": "6", "FanClub": "", "Active": "Yes", "Views": "925.571.965", "Likes": "18.355.165"}, "143": {"Profile": "https://dbkpop.com/group/bvndit/", "Name": "BVNDIT", "Short Name": "", "Korean Name": "\ubc34\ub514\ud2b8", "Debut": "2019-04-10", "Company": "MNH", "Current Member Count": "5", "Original Member Count": "5", "FanClub": "", "Active": "Yes", "Views": "36.553.464", "Likes": "1.050.659"}, "144": {"Profile": "https://dbkpop.com/group/episode/", "Name": "Episode", "Short Name": "", "Korean Name": "\uc5d0\ud53c\uc18c\ub4dc", "Debut": "2020-02-04", "Company": "Pops", "Current Member Count": "5", "Original Member Count": "5", "FanClub": "", "Active": "Yes"}, "145": {"Profile": "https://dbkpop.com/group/cignature/", "Name": "cignature", "Short Name": "", "Korean Name": "\uc2dc\uadf8\ub2c8\ucc98", "Debut": "2020-02-04", "Company": "C9", "Current Member Count": "7", "Original Member Count": "7", "FanClub": "", "Active": "Yes"}, "146": {"Profile": "https://dbkpop.com/group/hinapia/", "Name": "Hinapia", "Short Name": "", "Korean Name": "\ud76c\ub098\ud53c\uc544", "Debut": "2019-11-03", "Company": "Alseulbit", "Current Member Count": "5", "Original Member Count": "5", "FanClub": "", "Active": "No"}, "147": {"Profile": "https://dbkpop.com/group/3ye/", "Name": "3YE", "Short Name": "", "Korean Name": "\uc368\ub4dc\uc544\uc774", "Debut": "2019-05-21", "Company": "GH", "Current Member Count": "3", "Original Member Count": "3", "FanClub": "", "Active": "Yes", "Views": "26.119.453", "Likes": "1.190.587"}, "148": {"Profile": "https://dbkpop.com/group/rockit-girl/", "Name": "Rockit Girl", "Short Name": "", "Korean Name": "\ub77d\ud0b7\uac78", "Debut": "2019-05-30", "Company": "Rolling", "Current Member Count": "2", "Original Member Count": "2", "FanClub": "", "Active": "Yes"}, "149": {"Profile": "https://dbkpop.com/group/ariaz/", "Name": "Ariaz", "Short Name": "", "Korean Name": "\uc544\ub9ac\uc544\uc988", "Debut": "2019-10-23", "Company": "Rising Star", "Current Member Count": "6", "Original Member Count": "6", "FanClub": "", "Active": "Yes"}, "150": {"Profile": "https://dbkpop.com/group/ans/", "Name": "ANS", "Short Name": "", "Korean Name": "\uc5d0\uc774\uc5d4\uc5d0\uc2a4", "Debut": "2019-09-16", "Company": "ANS", "Current Member Count": "8", "Original Member Count": "6", "FanClub": "", "Active": "No"}, "151": {"Profile": "", "Name": "HighSchool", "Short Name": "", "Korean Name": "\uc5ec\uace0\uc0dd", "Debut": "2019-04-30", "Company": "Richworld", "Current Member Count": "4", "Original Member Count": "4", "FanClub": "High Class", "Active": "Yes"}, "152": {"Profile": "https://dbkpop.com/group/weeekly", "Name": "Weeekly", "Short Name": "", "Korean Name": "\uc704\ud074\ub9ac", "Debut": "2020-07-30", "Company": "Play M", "Current Member Count": "7", "Original Member Count": "7", "FanClub": "", "Active": "Yes", "Views": "225.067.618", "Likes": "4.154.803"}, "153": {"Profile": "https://dbkpop.com/group/craxy", "Name": "CRAXY", "Short Name": "", "Korean Name": "\ud06c\ub799\uc2dc", "Debut": "2020-03-03", "Company": "SAITEINMENT", "Current Member Count": "5", "Original Member Count": "5", "FanClub": "", "Active": "Yes"}, "154": {"Profile": "", "Name": "KEEMBO", "Short Name": "", "Korean Name": "\ud0b4\ubcf4", "Debut": "2020-04-10", "Company": "ARA-LINE", "Current Member Count": "2", "Original Member Count": "2", "FanClub": "", "Active": "Yes"}, "155": {"Profile": "https://dbkpop.com/group/redsquare", "Name": "REDSQUARE", "Short Name": "RSQ", "Korean Name": "\ub808\ub4dc\uc2a4\ud018\uc5b4", "Debut": "2020-05-19", "Company": "About", "Current Member Count": "5", "Original Member Count": "5", "FanClub": "", "Active": "Yes"}, "156": {"Profile": "https://dbkpop.com/group/secret-number", "Name": "SECRET NUMBER", "Short Name": "", "Korean Name": "\uc2dc\ud06c\ub9bf\ub118\ubc84", "Debut": "2020-05-19", "Company": "Vine", "Current Member Count": "5", "Original Member Count": "5", "FanClub": "", "Active": "Yes", "Views": "97.437.026", "Likes": "5.171.212"}, "157": {"Profile": "https://dbkpop.com/group/wooah", "Name": "woo!ah!", "Short Name": "", "Korean Name": "\uc6b0\uc544", "Debut": "2020-05-15", "Company": "NV", "Current Member Count": "5", "Original Member Count": "6", "FanClub": "", "Active": "Yes", "Views": "29.281.500", "Likes": "899.666"}, "158": {"Profile": "", "Name": "API", "Short Name": "", "Korean Name": "\uc5d0\uc774\ud53c\uc544\uc774", "Debut": "2019-04-19", "Company": "BRICKWORKS", "Current Member Count": "5", "Original Member Count": "5", "FanClub": "", "Active": "Yes", "Views": "845.695.326", "Likes": "9.173.569"}, "159": {"Profile": "", "Name": "FANATICS", "Short Name": "", "Korean Name": "\ud30c\ub098\ud2f1\uc2a4", "Debut": "2019-08-06", "Company": "FENT", "Current Member Count": "8", "Original Member Count": "6", "FanClub": "", "Active": "Yes"}, "160": {"Profile": "", "Name": "ILUV", "Short Name": "I LUV", "Korean Name": "\uc544\uc774\ub7ec\ube0c", "Debut": "2019-04-30", "Company": "WKS ENE", "Current Member Count": "7", "Original Member Count": "7", "FanClub": "", "Active": "No"}, "161": {"Profile": "", "Name": "Melody Pink", "Short Name": "", "Korean Name": "\uba5c\ub85c\ub514\ud551\ud06c", "Debut": "2019-09-25", "Company": "KD", "Current Member Count": "4", "Original Member Count": "4", "FanClub": "", "Active": "Yes"}, "162": {"Profile": "https://dbkpop.com/group/rocket-punch", "Name": "Rocket Punch", "Short Name": "", "Korean Name": "\ub85c\ucf13\ud380\uce58", "Debut": "2019-08-07", "Company": "Woollim", "Current Member Count": "6", "Original Member Count": "6", "FanClub": "", "Active": "Yes", "Views": "86.407.469", "Likes": "1.297.289"}, "163": {"Profile": "", "Name": "ICU", "Short Name": "", "Korean Name": "\uc544\uc774\uc528\uc720", "Debut": "2019-10-22", "Company": "Liz", "Current Member Count": "5", "Original Member Count": "5", "FanClub": "", "Active": "Yes"}, "164": {"Profile": "https://dbkpop.com/group/bling-bling/", "Name": "Bling Bling", "Short Name": "", "Korean Name": "\ube14\ub9c1\ube14\ub9c1", "Debut": "2020-11-17", "Company": "Major9", "Current Member Count": "6", "Original Member Count": "6", "FanClub": "", "Active": "Yes"}, "165": {"Profile": "https://dbkpop.com/group/stayc", "Name": "STAYC", "Short Name": "", "Korean Name": "\uc2a4\ud14c\uc774\uc528", "Debut": "2020-11-12", "Company": "Hi-Up", "Current Member Count": "6", "Original Member Count": "6", "FanClub": "", "Active": "Yes", "Views": "230.397.443", "Likes": "5.903.494"}, "166": {"Profile": "https://dbkpop.com/group/precious", "Name": "Precious", "Short Name": "PRCS", "Korean Name": "\ud504\ub808\uc154\uc2a4", "Debut": "2020-09-23", "Company": "Umi", "Current Member Count": "5", "Original Member Count": "5", "FanClub": "", "Active": "Yes"}, "167": {"Profile": "https://dbkpop.com/group/xum", "Name": "XUM", "Short Name": "", "Korean Name": "\uc378", "Debut": "2020-09-22", "Company": "A100", "Current Member Count": "3", "Original Member Count": "3", "FanClub": "AWEXUM", "Active": "No"}, "168": {"Profile": "https://dbkpop.com/group/neonpunch", "Name": "NeonPunch", "Short Name": "", "Korean Name": "\ub124\uc628\ud380\uce58", "Debut": "2018-06-27", "Company": "A100", "Current Member Count": "5", "Original Member Count": "5", "FanClub": "", "Active": "No"}, "169": {"Profile": "https://dbkpop.com/group/maka-maka", "Name": "Maka Maka", "Short Name": "", "Korean Name": "\ub9c8\uce74\ub9c8\uce74", "Debut": "2020-08-04", "Company": "Dreamus", "Current Member Count": "5", "Original Member Count": "5", "FanClub": "", "Active": "Yes"}, "170": {"Profile": "https://dbkpop.com/group/blastar", "Name": "Blastar", "Short Name": "", "Korean Name": "\ube14\ub808\uc2a4\ud0c0", "Debut": "2020-07-31", "Company": "VH", "Current Member Count": "5", "Original Member Count": "5", "FanClub": "", "Active": "No"}, "171": {"Profile": "", "Name": "BlackSwan", "Short Name": "", "Korean Name": "\ube14\ub799\uc2a4\uc644", "Debut": "2020-10-16", "Company": "DR", "Current Member Count": "5", "Original Member Count": "5", "FanClub": "", "Active": "Yes", "Views": "15.680.624", "Likes": "1.614.888"}, "172": {"Profile": "", "Name": "BOTOPASS", "Short Name": "", "Korean Name": "\ubcf4\ud1a0\ud328\uc2a4", "Debut": "2020-08-26", "Company": "WKS ENE", "Current Member Count": "8", "Original Member Count": "8", "FanClub": "", "Active": "Yes"}, "173": {"Profile": "https://dbkpop.com/group/lunarsolar/", "Name": "LUNARSOLAR", "Short Name": "", "Korean Name": "\ub8e8\ub098\uc194\ub77c", "Debut": "2020-09-02", "Company": "J Planet", "Current Member Count": "4", "Original Member Count": "4", "FanClub": "Haedal", "Active": "Yes"}, "174": {"Profile": "", "Name": "aespa", "Short Name": "\u00e6spa", "Korean Name": "\uc5d0\uc2a4\ud30c", "Debut": "2020-11-17", "Company": "SM", "Current Member Count": "4", "Original Member Count": "4", "FanClub": "My", "Active": "Yes", "Views": "901.178.347", "Likes": "20.470.627"}, "175": {"Profile": "", "Name": "AREAL", "Short Name": "", "Korean Name": "\uc5d0\uc774\ub9ac\uc5bc", "Debut": "2020-08-21", "Company": "JZ Factory", "Current Member Count": "4", "Original Member Count": "4", "FanClub": "", "Active": "Yes"}, "176": {"Profile": "https://dbkpop.com/group/tri-be/", "Name": "TRI.BE", "Short Name": "", "Korean Name": "\ud2b8\ub77c\uc774\ube44", "Debut": "2021-02-17", "Company": "TR - Mellow", "Current Member Count": "7", "Original Member Count": "7", "FanClub": "", "Active": "Yes", "Views": "57.781.533", "Likes": "1.202.086"}, "177": {"Profile": "https://dbkpop.com/group/pixy/", "Name": "PIXY", "Short Name": "", "Korean Name": "\ud53d\uc2dc", "Debut": "2021-02-24", "Company": "ALLART", "Current Member Count": "6", "Original Member Count": "6", "FanClub": "Winxy", "Active": "Yes"}, "178": {"Profile": "https://dbkpop.com/group/purple-kiss/", "Name": "Purple Kiss", "Short Name": "", "Korean Name": "\ud37c\ud50c\ud0a4\uc2a4", "Debut": "2021-03-15", "Company": "RBW", "Current Member Count": "7", "Original Member Count": "7", "FanClub": "", "Active": "Yes", "Views": "62.937.255", "Likes": "1.615.836"}, "179": {"Profile": "", "Name": "MAJORS", "Short Name": "", "Korean Name": "\uba54\uc774\uc838\uc2a4", "Debut": "2021-03-09", "Company": "ANS", "Current Member Count": "6", "Original Member Count": "6", "FanClub": "MVP", "Active": "Yes"}, "180": {"Profile": "", "Name": "PRISMA", "Short Name": "", "Korean Name": "\ud504\ub9ac\uc988\ub9c8", "Debut": "2020-10-31", "Company": "UnionWave", "Current Member Count": "5", "Original Member Count": "5", "FanClub": "", "Active": "Yes"}, "181": {"Profile": "https://dbkpop.com/group/ioi/", "Name": "IOI", "Short Name": "I.O.I", "Korean Name": "\uc544\uc774\uc624\uc544\uc774", "Debut": "2016-05-04", "Company": "YMC", "Current Member Count": "11", "Original Member Count": "11", "FanClub": "", "Active": "No"}, "182": {"Profile": "https://dbkpop.com/group/ichillin/", "Name": "ICHILLIN'", "Short Name": "", "Korean Name": "\uc544\uc774\uce60\ub9b0", "Debut": "2021-09-08", "Company": "KM", "Current Member Count": "7", "Original Member Count": "7", "FanClub": "", "Active": "Yes"}, "183": {"Profile": "https://dbkpop.com/group/billlie/", "Name": "Billlie", "Short Name": "", "Korean Name": "\ube4c\ub9ac", "Debut": "", "Company": "MYSTIC", "Current Member Count": "6", "Original Member Count": "6", "FanClub": "", "Active": "Yes"}, "184": {"Profile": "https://dbkpop.com/group/viviz/", "Name": "VIVIZ", "Short Name": "", "Korean Name": "\ube44\ube44\uc9c0", "Debut": "", "Company": "Big Planet Made", "Current Member Count": "3", "Original Member Count": "3", "FanClub": "", "Active": "Yes", "Views": "19.753.220", "Likes": "1.111.011"}, "185": {"Profile": "https://dbkpop.com/group/lightsum/", "Name": "LIGHTSUM", "Short Name": "", "Korean Name": "\ub77c\uc787\uc378", "Debut": "2021-06-10", "Company": "Cube", "Current Member Count": "8", "Original Member Count": "8", "FanClub": "SUMIT", "Active": "Yes"}, "186": {"Profile": "", "Name": "PRITTI-G", "Short Name": "", "Korean Name": "\ud504\ub9ac\ud2f0\uc9c0", "Debut": "2021-08-31", "Company": "Enterrobang", "Current Member Count": "6", "Original Member Count": "6", "FanClub": "", "Active": "Yes"}, "187": {"Profile": "", "Name": "Solia", "Short Name": "", "Korean Name": "\uc3e0\ub9ac\uc544", "Debut": "2021-08-17", "Company": "Space", "Current Member Count": "5", "Original Member Count": "5", "FanClub": "", "Active": "No"}, "188": {"Profile": "https://dbkpop.com/group/bugbaboo/", "Name": "bugAboo", "Short Name": "", "Korean Name": "\ubc84\uac00\ubd80", "Debut": "2021-10-25", "Company": "A team", "Current Member Count": "6", "Original Member Count": "6", "FanClub": "", "Active": "Yes"}, "189": {"Profile": "", "Name": "SKYLE", "Short Name": "", "Korean Name": "\uc2a4\uce74\uc774\ub9ac", "Debut": "2021-08-04", "Company": "Good Luck", "Current Member Count": "4", "Original Member Count": "4", "FanClub": "", "Active": "Yes"}, "190": {"Profile": "", "Name": "Rumble-G", "Short Name": "", "Korean Name": "\ub7fc\ube14\uc9c0", "Debut": "2021-07-14", "Company": "Winnerzone", "Current Member Count": "4", "Original Member Count": "4", "FanClub": "", "Active": "Yes"}}